{"questions":[{"question":"What is ICR?","answer":"Intelligent Character Recognition (Good)"},{"question":"What are the various Data export formats?","answer":"All of the options mentioned (Good)"},{"question":"What are the various document Processing Stages?","answer":"All of the options mentioned (Good)"},{"question":"How many language texts ABBYY technologies can recognize?","answer":"upto 200 (Good)"},{"question":"What are ABBYY image import options?","answer":"All of the options mentioned (Good)"},{"question":"What is OCR?","answer":" Optical Character Recognition (Good)"},{"question":"What are the challenges in Manual Data Entry and Processing?","answer":"All of the options mentioned (Good)"},{"question":"What type of documents ABBYY Flexicapture can process?","answer":"All of the options mentioned (Good)"},{"question":"Assembly errors can be corrected in which station?","answer":"Verification Station (Good)"},{"question":"Which of the following actions can be performed in Data Verification station?","answer":"Check uncertain characters, data format (Good)"},{"question":"What are various Verification Operator roles?","answer":"All of the options (Good) "},{"question":"Which one is ABBYY Flexicapture Server Component?","answer":"File Storage (Good)"},{"question":"Which of the following actions can be performed in scanning station?","answer":"Send batches containing images to server for recognition (Good)"},{"question":"Data Verification Operator works on which station?","answer":"Data Verification Station (Good)"},{"question":"What are the tasks handled in Verification station?","answer":"All of the options (Good)"},{"question":"What are ABBYY Flexicapture installation types?","answer":"Both (Good) "},{"question":"Which component distributes the tasks among the processing stations?","answer":"Processing Server (Good) "},{"question":"Data verification station can be accessed ---------------","answer":"Both (Good) "},{"question":"Which station is used to create Flexicapture project?","answer":" Project Setup (Good) "},{"question":"The order in which Document Definitions are applied?","answer":"First Structured, then Semi-structured in the order they appear in the list (Good)"},{"question":"What information is contained in the Flexicapture Project?","answer":"All of the options mentioned (Good)"},{"question":"Which one is ABBYY Flexicapture Client Component?","answer":"Project Setup Station (Good)"},{"question":"What information is stired in DB server?","answer":"All of the options mentioned (Good)"},{"question":"A section of a Document Definition consists of ________.","answer":"One or more pages (Good)"},{"question":"What is a Document Set used for?","answer":"To reduce verification time spent on document package integrity check, and to quickly compare main fields with child documents."},{"question":"What are Batch Types used for?","answer":"All the options (Good)"},{"question":"What are the tasks handled in a Verification station?","answer":"All the options (Good)"},{"question":"On which station can you create a Document Definition?","answer":"Project Setup Station (Good)"},{"question":"In which order will FlexiCapture match definitions to images, if there are multiple document definitions of both structured (Fixed Form) and semi-structured (FlexiLayout) types?","answer":"In the order they are published (Good)"},{"question":"What is a Document Definition used for?","answer":"To specify the fields to be recognized and the document processing parameters. (Good)"},{"question":"On which station can Validation Rule errors (e.g. Script rule or DB check) be corrected?","answer":"Verification Station (Good)"},{"question":"Images can be imported to a project by using?","answer":"All the options Good)"},{"question":"An Operator with role Data Verification Operator can work on?","answer":"All the options Good)"},{"question":"What type of documents can ABBYY FlexiCapture process?","answer":"All the options (Good)"},{"question":"Is it possible to export all batches immediately after recognition, without any verification by operators?","answer":"Yes, if Unattended or specially Customized Advanced Workflow is used. (Good)"},{"question":"Which of the following statements is true about Image Import profiles?","answer":"Several import profiles can be created by using different storages for various batch types. (Good)"}]}